{
   "version":"1.0",
   "encoding":"UTF-8",
   "feed":{
      "xmlns":"http://www.w3.org/2005/Atom",
      "xmlns$openSearch":"http://a9.com/-/spec/opensearchrss/1.0/",
      "xmlns$gsx":"http://schemas.google.com/spreadsheets/2006/extended",
      "id":{
         "$t":"https://spreadsheets.google.com/feeds/list/1oiiPeRnUPX32MkmG8NFB0IauLrWtjoiEMQsE0sCRQ6I/od6/public/values?alt=json"
      },
      "updated":{
         "$t":"2015-02-26T13:02:02.845Z"
      },
      "category":[
         {
            "scheme":"http://schemas.google.com/spreadsheets/2006",
            "term":"http://schemas.google.com/spreadsheets/2006#list"
         }
      ],
      "title":{
         "type":"text",
         "$t":"Tabellenblatt1"
      },
      "link":[
         {
            "rel":"alternate",
            "type":"application/atom+xml",
            "href":"https://docs.google.com/spreadsheets/d/1oiiPeRnUPX32MkmG8NFB0IauLrWtjoiEMQsE0sCRQ6I/pubhtml"
         },
         {
            "rel":"http://schemas.google.com/g/2005#feed",
            "type":"application/atom+xml",
            "href":"https://spreadsheets.google.com/feeds/list/1oiiPeRnUPX32MkmG8NFB0IauLrWtjoiEMQsE0sCRQ6I/od6/public/values"
         },
         {
            "rel":"http://schemas.google.com/g/2005#post",
            "type":"application/atom+xml",
            "href":"https://spreadsheets.google.com/feeds/list/1oiiPeRnUPX32MkmG8NFB0IauLrWtjoiEMQsE0sCRQ6I/od6/public/values"
         },
         {
            "rel":"self",
            "type":"application/atom+xml",
            "href":"https://spreadsheets.google.com/feeds/list/1oiiPeRnUPX32MkmG8NFB0IauLrWtjoiEMQsE0sCRQ6I/od6/public/values?alt\u003djson"
         }
      ],
      "author":[
         {
            "name":{
               "$t":"christoph.labacher"
            },
            "email":{
               "$t":"christoph.labacher@gmail.com"
            }
         }
      ],
      "openSearch$totalResults":{
         "$t":"4"
      },
      "openSearch$startIndex":{
         "$t":"1"
      },
      "entry":[
         {
            "id":{
               "$t":"https://spreadsheets.google.com/feeds/list/1oiiPeRnUPX32MkmG8NFB0IauLrWtjoiEMQsE0sCRQ6I/od6/public/values/cokwr"
            },
            "updated":{
               "$t":"2015-02-26T13:02:02.845Z"
            },
            "category":[
               {
                  "scheme":"http://schemas.google.com/spreadsheets/2006",
                  "term":"http://schemas.google.com/spreadsheets/2006#list"
               }
            ],
            "title":{
               "type":"text",
               "$t":"Maximilian"
            },
            "content":{
               "type":"text",
               "$t":"name: Mustermann-Müller, birthdate: 13.04.1949, patientid: 123135267847, caseid: 2258248, station: Neuro, stationphone: 2598, stationroom: 2137, diagnosis: Implementation zementfreie HTP li., service: Lobotomie, risk: Keine außerordentlichen Risiken., comment: 48 ZAC 09:00, Restkolektomie, surgeryteam: AVJ, AJW, BAP, surgeryroom: 1, starttime: 2014-12-08T04:30:00, endtime: 2014-12-08T06:00:00, currentstate: 1"
            },
            "link":[
               {
                  "rel":"self",
                  "type":"application/atom+xml",
                  "href":"https://spreadsheets.google.com/feeds/list/1oiiPeRnUPX32MkmG8NFB0IauLrWtjoiEMQsE0sCRQ6I/od6/public/values/cokwr"
               }
            ],
            "gsx$prename":{
               "$t":"Maximilian"
            },
            "gsx$name":{
               "$t":"Mustermann-Müller"
            },
            "gsx$birthdate":{
               "$t":"13.04.1949"
            },
            "gsx$patientid":{
               "$t":"123135267847"
            },
            "gsx$caseid":{
               "$t":"2258248"
            },
            "gsx$station":{
               "$t":"Neuro"
            },
            "gsx$stationphone":{
               "$t":"2598"
            },
            "gsx$stationroom":{
               "$t":"2137"
            },
            "gsx$diagnosis":{
               "$t":"Implementation zementfreie HTP li."
            },
            "gsx$service":{
               "$t":"Lobotomie"
            },
            "gsx$risk":{
               "$t":"Keine außerordentlichen Risiken."
            },
            "gsx$comment":{
               "$t":"48 ZAC 09:00, Restkolektomie"
            },
            "gsx$surgeryteam":{
               "$t":"AVJ, AJW, BAP"
            },
            "gsx$surgeryroom":{
               "$t":"1"
            },
            "gsx$starttime":{
               "$t":"2014-12-08T04:30:00"
            },
            "gsx$endtime":{
               "$t":"2014-12-08T06:00:00"
            },
            "gsx$currentstate":{
               "$t":"1"
            },
            "gsx$state1timestamp":{
               "$t":""
            },
            "gsx$state2timestamp":{
               "$t":""
            },
            "gsx$state3timestamp":{
               "$t":""
            },
            "gsx$state4timestamp":{
               "$t":""
            },
            "gsx$state5timestamp":{
               "$t":""
            },
            "gsx$state6timestamp":{
               "$t":""
            },
            "gsx$state7timestamp":{
               "$t":""
            },
            "gsx$state8timestamp":{
               "$t":""
            },
            "gsx$state9timestamp":{
               "$t":""
            },
            "gsx$state10timestamp":{
               "$t":""
            },
            "gsx$state11timestamp":{
               "$t":""
            }
         },
         {
            "id":{
               "$t":"https://spreadsheets.google.com/feeds/list/1oiiPeRnUPX32MkmG8NFB0IauLrWtjoiEMQsE0sCRQ6I/od6/public/values/cpzh4"
            },
            "updated":{
               "$t":"2015-02-26T13:02:02.845Z"
            },
            "category":[
               {
                  "scheme":"http://schemas.google.com/spreadsheets/2006",
                  "term":"http://schemas.google.com/spreadsheets/2006#list"
               }
            ],
            "title":{
               "type":"text",
               "$t":"Felix"
            },
            "content":{
               "type":"text",
               "$t":"name: Neudorf, birthdate: 11.03.1987, patientid: 41245010364, caseid: 5256661, station: Allgemein, stationphone: 2578, stationroom: 1300, diagnosis: Pseudarthrose, service: Wirbelkörperfraktur, risk: Keine außerordentlichen Risiken., surgeryteam: ADH, SBR, PIS, surgeryroom: 3, starttime: 2014-12-08T05:00:00, endtime: 2014-12-08T06:45:00, currentstate: 2"
            },
            "link":[
               {
                  "rel":"self",
                  "type":"application/atom+xml",
                  "href":"https://spreadsheets.google.com/feeds/list/1oiiPeRnUPX32MkmG8NFB0IauLrWtjoiEMQsE0sCRQ6I/od6/public/values/cpzh4"
               }
            ],
            "gsx$prename":{
               "$t":"Felix"
            },
            "gsx$name":{
               "$t":"Neudorf"
            },
            "gsx$birthdate":{
               "$t":"11.03.1987"
            },
            "gsx$patientid":{
               "$t":"41245010364"
            },
            "gsx$caseid":{
               "$t":"5256661"
            },
            "gsx$station":{
               "$t":"Allgemein"
            },
            "gsx$stationphone":{
               "$t":"2578"
            },
            "gsx$stationroom":{
               "$t":"1300"
            },
            "gsx$diagnosis":{
               "$t":"Pseudarthrose"
            },
            "gsx$service":{
               "$t":"Wirbelkörperfraktur"
            },
            "gsx$risk":{
               "$t":"Keine außerordentlichen Risiken."
            },
            "gsx$comment":{
               "$t":""
            },
            "gsx$surgeryteam":{
               "$t":"ADH, SBR, PIS"
            },
            "gsx$surgeryroom":{
               "$t":"3"
            },
            "gsx$starttime":{
               "$t":"2014-12-08T05:00:00"
            },
            "gsx$endtime":{
               "$t":"2014-12-08T06:45:00"
            },
            "gsx$currentstate":{
               "$t":"2"
            },
            "gsx$state1timestamp":{
               "$t":""
            },
            "gsx$state2timestamp":{
               "$t":""
            },
            "gsx$state3timestamp":{
               "$t":""
            },
            "gsx$state4timestamp":{
               "$t":""
            },
            "gsx$state5timestamp":{
               "$t":""
            },
            "gsx$state6timestamp":{
               "$t":""
            },
            "gsx$state7timestamp":{
               "$t":""
            },
            "gsx$state8timestamp":{
               "$t":""
            },
            "gsx$state9timestamp":{
               "$t":""
            },
            "gsx$state10timestamp":{
               "$t":""
            },
            "gsx$state11timestamp":{
               "$t":""
            }
         },
         {
            "id":{
               "$t":"https://spreadsheets.google.com/feeds/list/1oiiPeRnUPX32MkmG8NFB0IauLrWtjoiEMQsE0sCRQ6I/od6/public/values/cre1l"
            },
            "updated":{
               "$t":"2015-02-26T13:02:02.845Z"
            },
            "category":[
               {
                  "scheme":"http://schemas.google.com/spreadsheets/2006",
                  "term":"http://schemas.google.com/spreadsheets/2006#list"
               }
            ],
            "title":{
               "type":"text",
               "$t":"Maximilian"
            },
            "content":{
               "type":"text",
               "$t":"name: Mustermann-Müller, birthdate: 13.04.1949, patientid: 123135267847, caseid: 2258248, station: Neuro, stationphone: 2598, stationroom: 2137, diagnosis: Implementation zementfreie HTP li., service: Lobotomie, risk: Keine außerordentlichen Risiken., comment: 48 ZAC 09:00, Restkolektomie, surgeryteam: AVJ, AJW, BAP, surgeryroom: 1, starttime: 2014-12-08T01:00:00, endtime: 2014-12-08T03:00:00, currentstate: 10"
            },
            "link":[
               {
                  "rel":"self",
                  "type":"application/atom+xml",
                  "href":"https://spreadsheets.google.com/feeds/list/1oiiPeRnUPX32MkmG8NFB0IauLrWtjoiEMQsE0sCRQ6I/od6/public/values/cre1l"
               }
            ],
            "gsx$prename":{
               "$t":"Maximilian"
            },
            "gsx$name":{
               "$t":"Mustermann-Müller"
            },
            "gsx$birthdate":{
               "$t":"13.04.1949"
            },
            "gsx$patientid":{
               "$t":"123135267847"
            },
            "gsx$caseid":{
               "$t":"2258248"
            },
            "gsx$station":{
               "$t":"Neuro"
            },
            "gsx$stationphone":{
               "$t":"2598"
            },
            "gsx$stationroom":{
               "$t":"2137"
            },
            "gsx$diagnosis":{
               "$t":"Implementation zementfreie HTP li."
            },
            "gsx$service":{
               "$t":"Lobotomie"
            },
            "gsx$risk":{
               "$t":"Keine außerordentlichen Risiken."
            },
            "gsx$comment":{
               "$t":"48 ZAC 09:00, Restkolektomie"
            },
            "gsx$surgeryteam":{
               "$t":"AVJ, AJW, BAP"
            },
            "gsx$surgeryroom":{
               "$t":"1"
            },
            "gsx$starttime":{
               "$t":"2014-12-08T01:00:00"
            },
            "gsx$endtime":{
               "$t":"2014-12-08T03:00:00"
            },
            "gsx$currentstate":{
               "$t":"10"
            },
            "gsx$state1timestamp":{
               "$t":""
            },
            "gsx$state2timestamp":{
               "$t":""
            },
            "gsx$state3timestamp":{
               "$t":""
            },
            "gsx$state4timestamp":{
               "$t":""
            },
            "gsx$state5timestamp":{
               "$t":""
            },
            "gsx$state6timestamp":{
               "$t":""
            },
            "gsx$state7timestamp":{
               "$t":""
            },
            "gsx$state8timestamp":{
               "$t":""
            },
            "gsx$state9timestamp":{
               "$t":""
            },
            "gsx$state10timestamp":{
               "$t":""
            },
            "gsx$state11timestamp":{
               "$t":""
            }
         },
         {
            "id":{
               "$t":"https://spreadsheets.google.com/feeds/list/1oiiPeRnUPX32MkmG8NFB0IauLrWtjoiEMQsE0sCRQ6I/od6/public/values/chk2m"
            },
            "updated":{
               "$t":"2015-02-26T13:02:02.845Z"
            },
            "category":[
               {
                  "scheme":"http://schemas.google.com/spreadsheets/2006",
                  "term":"http://schemas.google.com/spreadsheets/2006#list"
               }
            ],
            "title":{
               "type":"text",
               "$t":"Felix"
            },
            "content":{
               "type":"text",
               "$t":"name: Neudorf, birthdate: 11.03.1987, patientid: 41245010364, caseid: 5256661, station: Allgemein, stationphone: 2578, stationroom: 1300, diagnosis: Pseudarthrose, service: Wirbelkörperfraktur, risk: Keine außerordentlichen Risiken., surgeryteam: ADH, SBR, PIS, surgeryroom: 2, starttime: 2014-12-08T00:30:00, endtime: 2014-12-08T02:30:00, currentstate: 8"
            },
            "link":[
               {
                  "rel":"self",
                  "type":"application/atom+xml",
                  "href":"https://spreadsheets.google.com/feeds/list/1oiiPeRnUPX32MkmG8NFB0IauLrWtjoiEMQsE0sCRQ6I/od6/public/values/chk2m"
               }
            ],
            "gsx$prename":{
               "$t":"Felix"
            },
            "gsx$name":{
               "$t":"Neudorf"
            },
            "gsx$birthdate":{
               "$t":"11.03.1987"
            },
            "gsx$patientid":{
               "$t":"41245010364"
            },
            "gsx$caseid":{
               "$t":"5256661"
            },
            "gsx$station":{
               "$t":"Allgemein"
            },
            "gsx$stationphone":{
               "$t":"2578"
            },
            "gsx$stationroom":{
               "$t":"1300"
            },
            "gsx$diagnosis":{
               "$t":"Pseudarthrose"
            },
            "gsx$service":{
               "$t":"Wirbelkörperfraktur"
            },
            "gsx$risk":{
               "$t":"Keine außerordentlichen Risiken."
            },
            "gsx$comment":{
               "$t":""
            },
            "gsx$surgeryteam":{
               "$t":"ADH, SBR, PIS"
            },
            "gsx$surgeryroom":{
               "$t":"2"
            },
            "gsx$starttime":{
               "$t":"2014-12-08T00:30:00"
            },
            "gsx$endtime":{
               "$t":"2014-12-08T02:30:00"
            },
            "gsx$currentstate":{
               "$t":"8"
            },
            "gsx$state1timestamp":{
               "$t":""
            },
            "gsx$state2timestamp":{
               "$t":""
            },
            "gsx$state3timestamp":{
               "$t":""
            },
            "gsx$state4timestamp":{
               "$t":""
            },
            "gsx$state5timestamp":{
               "$t":""
            },
            "gsx$state6timestamp":{
               "$t":""
            },
            "gsx$state7timestamp":{
               "$t":""
            },
            "gsx$state8timestamp":{
               "$t":""
            },
            "gsx$state9timestamp":{
               "$t":""
            },
            "gsx$state10timestamp":{
               "$t":""
            },
            "gsx$state11timestamp":{
               "$t":""
            }
         }
      ]
   }
}